[
  {
    "full_name": "Rigellute/spotify-tui",
    "stargazers_count": 12964,
    "open_issues_count": 224,
    "forks_count": 415
  },
  {
    "full_name": "reviewdog/reviewdog",
    "stargazers_count": 5373,
    "open_issues_count": 94,
    "forks_count": 291
  },
  {
    "full_name": "kubernetes-sigs/controller-runtime",
    "stargazers_count": 1639,
    "open_issues_count": 124,
    "forks_count": 835
  },
  {
    "full_name": "chaos-mesh/chaos-mesh",
    "stargazers_count": 5109,
    "open_issues_count": 304,
    "forks_count": 647
  },
  {
    "full_name": "kubernetes/kubernetes",
    "stargazers_count": 91253,
    "open_issues_count": 2475,
    "forks_count": 33438
  },
  {
    "full_name": "open-sauced/open-sauced",
    "stargazers_count": 750,
    "open_issues_count": 17,
    "forks_count": 356
  }
]