[
  {
    "full_name": "facebook/sapling",
    "stargazers_count": 2691,
    "open_issues_count": 41,
    "forks_count": 112
  },
  {
    "full_name": "anymaniax/orval",
    "stargazers_count": 875,
    "open_issues_count": 90,
    "forks_count": 115
  },
  {
    "full_name": "ent/ent",
    "stargazers_count": 12367,
    "open_issues_count": 276,
    "forks_count": 719
  },
  {
    "full_name": "self-actuated/actuated",
    "stargazers_count": 88,
    "open_issues_count": 0,
    "forks_count": 1
  },
  {
    "full_name": "artginzburg/sudo-touchid",
    "stargazers_count": 234,
    "open_issues_count": 6,
    "forks_count": 6
  },
  {
    "full_name": "hfg-gmuend/openmoji",
    "stargazers_count": 2527,
    "open_issues_count": 33,
    "forks_count": 165
  },
  {
    "full_name": "nextauthjs/next-auth",
    "stargazers_count": 12353,
    "open_issues_count": 166,
    "forks_count": 1501
  },
  {
    "full_name": "TanStack/query",
    "stargazers_count": 31106,
    "open_issues_count": 27,
    "forks_count": 1919
  },
  {
    "full_name": "emilk/egui",
    "stargazers_count": 11795,
    "open_issues_count": 294,
    "forks_count": 812
  },
  {
    "full_name": "bevyengine/bevy",
    "stargazers_count": 20254,
    "open_issues_count": 1320,
    "forks_count": 1998
  },
  {
    "full_name": "snok/container-retention-policy",
    "stargazers_count": 67,
    "open_issues_count": 9,
    "forks_count": 11
  },
  {
    "full_name": "kubernetes-sigs/bom",
    "stargazers_count": 163,
    "open_issues_count": 18,
    "forks_count": 23
  },
  {
    "full_name": "lowlighter/metrics",
    "stargazers_count": 8872,
    "open_issues_count": 10,
    "forks_count": 1019
  },
  {
    "full_name": "CodeEditApp/CodeEdit",
    "stargazers_count": 15488,
    "open_issues_count": 110,
    "forks_count": 737
  },
  {
    "full_name": "gschup/ggrs",
    "stargazers_count": 261,
    "open_issues_count": 4,
    "forks_count": 12
  },
  {
    "full_name": "deepnight/ldtk",
    "stargazers_count": 2217,
    "open_issues_count": 188,
    "forks_count": 121
  },
  {
    "full_name": "kubernetes-sigs/kube-storage-version-migrator",
    "stargazers_count": 98,
    "open_issues_count": 7,
    "forks_count": 52
  },
  {
    "full_name": "opencost/opencost",
    "stargazers_count": 2989,
    "open_issues_count": 137,
    "forks_count": 295
  },
  {
    "full_name": "BrunoLevy/learn-fpga",
    "stargazers_count": 1211,
    "open_issues_count": 33,
    "forks_count": 121
  },
  {
    "full_name": "concourse/concourse",
    "stargazers_count": 6657,
    "open_issues_count": 873,
    "forks_count": 829
  },
  {
    "full_name": "InitWare/InitWare",
    "stargazers_count": 160,
    "open_issues_count": 17,
    "forks_count": 3
  },
  {
    "full_name": "kubereboot/kured",
    "stargazers_count": 1597,
    "open_issues_count": 39,
    "forks_count": 180
  },
  {
    "full_name": "openfga/openfga",
    "stargazers_count": 615,
    "open_issues_count": 29,
    "forks_count": 34
  },
  {
    "full_name": "IdreesInc/Monocraft",
    "stargazers_count": 5449,
    "open_issues_count": 31,
    "forks_count": 68
  },
  {
    "full_name": "sloganking/codevis",
    "stargazers_count": 189,
    "open_issues_count": 10,
    "forks_count": 6
  },
  {
    "full_name": "NextAlone/Nagram",
    "stargazers_count": 139,
    "open_issues_count": 3,
    "forks_count": 17
  },
  {
    "full_name": "ubershmekel/vite-phaser-ts-starter",
    "stargazers_count": 40,
    "open_issues_count": 0,
    "forks_count": 5
  },
  {
    "full_name": "photonstorm/phaser",
    "stargazers_count": 33138,
    "open_issues_count": 126,
    "forks_count": 6847
  },
  {
    "full_name": "greenheartgames/greenworks",
    "stargazers_count": 1334,
    "open_issues_count": 58,
    "forks_count": 148
  },
  {
    "full_name": "Kr328/ClashForAndroid",
    "stargazers_count": 17876,
    "open_issues_count": 95,
    "forks_count": 2143
  }
]